Metadata-Version: 2.4
Name: mcp-server-larf
Version: 0.1.0
Summary: A lightweight MCP server for LARF with OpenAI integration
Requires-Python: >=3.12
Requires-Dist: dotenv>=0.9.9
Requires-Dist: mcp>=1.14.1
Requires-Dist: openai>=1.108.1
